{
  "project_info": {
    "project_number": "403928543583",
    "project_id": "uas-moprog2",
    "storage_bucket": "uas-moprog2.appspot.com"
  },
  "client": [
    {
      "client_info": {
        "mobilesdk_app_id": "1:403928543583:android:d31ee34a0bb122dc3446ea",
        "android_client_info": {
          "package_name": "com.example.uas_moprog2"
        }
      },
      "oauth_client": [],
      "api_key": [
        {
          "current_key": "AIzaSyA_fvXpzxNdjjg_Fj9W8IMOEDuHKsKa1zc"
        }
      ],
      "services": {
        "appinvite_service": {
          "other_platform_oauth_client": []
        }
      }
    }
  ],
  "configuration_version": "1"
}